yaml_config_processor/__init__.py
yaml_config_processor/_version.py
yaml_config_processor/processor.py
yaml_config_processor-0.2.13.dist-info/licenses/LICENSE
yaml_config_processor-0.2.13.dist-info/METADATA
yaml_config_processor-0.2.13.dist-info/WHEEL
yaml_config_processor-0.2.13.dist-info/top_level.txt
yaml_config_processor-0.2.13.dist-info/RECORD
