Metadata-Version: 2.4
Name: yaml-config-processor
Version: 0.2.13
Summary: Process YAML templates with JSON configurations
Author-email: Serhii Setti <serhii.setti@pm.me>
License: MIT License
Project-URL: Homepage, https://github.com/SergeySetti/yaml-config-processor
Project-URL: Bug Tracker, https://github.com/SergeySetti/yaml-config-processor/issues
Classifier: Programming Language :: Python :: 3
Classifier: Programming Language :: Python :: 3.7
Classifier: Programming Language :: Python :: 3.8
Classifier: Programming Language :: Python :: 3.9
Classifier: Programming Language :: Python :: 3.10
Classifier: Programming Language :: Python :: 3.11
Classifier: Programming Language :: Python :: 3.12
Classifier: License :: OSI Approved :: MIT License
Classifier: Operating System :: OS Independent
Classifier: Development Status :: 4 - Beta
Classifier: Intended Audience :: Developers
Classifier: Topic :: Software Development :: Libraries :: Python Modules
Requires-Python: >=3.7
License-File: LICENSE
Requires-Dist: pyyaml>=5.1
Requires-Dist: jsonschema>=3.2.0
Dynamic: license-file
